gglconsole/__init__.py
gglconsole/gglconsole.py
gglconsole-0.2.3.dist-info/LICENSE
gglconsole-0.2.3.dist-info/METADATA
gglconsole-0.2.3.dist-info/WHEEL
gglconsole-0.2.3.dist-info/entry_points.txt
gglconsole-0.2.3.dist-info/top_level.txt
gglconsole-0.2.3.dist-info/RECORD
