Metadata-Version: 2.1
Name: gglconsole
Version: 0.2.3
Summary: GGLConsole provides you the command line interface for websearch by Google / Bing.
Home-page: https://github.com/uezo/gglconsole
Author: uezo
Author-email: uezo@uezo.net
Maintainer: uezo
Maintainer-email: uezo@uezo.net
License: Apache v2
Platform: UNKNOWN
Requires-Dist: requests
Requires-Dist: rich
